he_kit/__init__.py
he_kit/cli.py
he_kit/authn/base.py
he_kit/authn/dependencies.py
he_kit/authn/dummy.py
he_kit/authn/keycloak.py
he_kit/authn/loader.py
he_kit/core/__init__.py
he_kit/core/app.py
he_kit/core/conf.py
he_kit/core/db.py
he_kit/core/lifespan.py
he_kit/core/logging.py
he_kit/templates/.dockerignore
he_kit/templates/.gitignore
he_kit/templates/.pre-commit-config.yaml
he_kit/templates/Dockerfile
he_kit/templates/README.md.j2
he_kit/templates/alembic.ini
he_kit/templates/main.py.j2
he_kit/templates/pyproject.toml.j2
he_kit/templates/migrations/env.py.j2
he_kit/templates/migrations/script.py.mako
he_kit/templates/migrations/versions/placeholder.txt
he_kit/templates/src/{{module_name}}/__init__.py
he_kit/templates/src/{{module_name}}/app.py
he_kit/templates/src/{{module_name}}/conf.py
he_kit/templates/src/{{module_name}}/models/__init__.py
he_kit/templates/src/{{module_name}}/routers/__init__.py
he_kit/templates/src/{{module_name}}/schemas/__init__.py
he_kit/templates/tests/conftest.py.j2
he_kit/testing/__init__.py
he_kit/testing/container_db.py
he_kit/testing/fixtures.py
he_kit/utils/__init__.py
he_kit/utils/alembic.py
he_kit/utils/project.py
he_kit/utils/templating.py
he_kit-0.0.19.dist-info/METADATA
he_kit-0.0.19.dist-info/WHEEL
he_kit-0.0.19.dist-info/entry_points.txt
he_kit-0.0.19.dist-info/RECORD
