Metadata-Version: 2.4
Name: he-kit
Version: 0.0.19
Summary: A project generator that bootstraps a FastAPI setup following Helicon's standards and best practices.
Author-email: gs <gs@helicon.ai>
Requires-Python: >=3.12
Requires-Dist: aiosqlite>=0.21.0
Requires-Dist: alembic>=1.17.0
Requires-Dist: fastapi[standard]>=0.119.1
Requires-Dist: pydantic-settings>=2.11.0
Requires-Dist: pyjwt>=2.10.1
Requires-Dist: sqlalchemy>=2.0.44
Requires-Dist: sqlmodel>=0.0.27
Requires-Dist: structlog>=25.4.0
Provides-Extra: keycloak
Requires-Dist: python-keycloak>=4.6.0; extra == 'keycloak'
